experiment-4/binary_to_excess3.v
module binary_to_excess3 (
    input [3:0] binary,  // 4-bit Binary input
    output [3:0] excess3 // 4-bit Excess-3 output
);

    // Conversion logic: Excess-3 = Binary + 3
    assign excess3 = binary + 4'b0011;  // Add 3 (0011 in binary)

endmodule

experiment-4/tb_binary_to_excess3.v
`timescale 1ns / 1ps

module tb_binary_to_excess3;
    // Inputs
    reg [3:0] binary;
    
    // Outputs
    wire [3:0] excess3;
    
    // Instantiate the Unit Under Test (UUT)
    binary_to_excess3 uut (
        .binary(binary),
        .excess3(excess3)
    );

    // Simulation control
    initial begin
        // Create VCD file for waveform dumping
        $dumpfile("binary_to_excess3.vcd");   // Create the VCD file
        $dumpvars(0, tb_binary_to_excess3);   // Dump all variables of the testbench

        // Display output on the console
        $monitor("Time = %0d, Binary = %b, Excess-3 = %b", $time, binary, excess3);
        
        // Test cases
        binary = 4'b0000; #10;  // 0  -> 3 (Excess-3)
        binary = 4'b0001; #10;  // 1  -> 4
        binary = 4'b0010; #10;  // 2  -> 5
        binary = 4'b0011; #10;  // 3  -> 6
        binary = 4'b0100; #10;  // 4  -> 7
        binary = 4'b0101; #10;  // 5  -> 8
        binary = 4'b0110; #10;  // 6  -> 9
        binary = 4'b0111; #10;  // 7  -> 10 (out of valid BCD range, but valid result)
        binary = 4'b1000; #10;  // 8  -> 11
        binary = 4'b1001; #10;  // 9  -> 12
        binary = 4'b1010; #10;  // 10 -> 13 (Invalid BCD but valid excess-3 output)
        binary = 4'b1011; #10;  // 11 -> 14
        binary = 4'b1100; #10;  // 12 -> 15
        binary = 4'b1101; #10;  // 13 -> 16
        binary = 4'b1110; #10;  // 14 -> 17
        binary = 4'b1111; #10;  // 15 -> 18

        // End simulation
        $finish;
    end
endmodule

experiment-4/binary_to_excess3.vcd
$date
	Thu Oct  3 19:15:56 2024
$end
$version
	Icarus Verilog
$end
$timescale
	1ps
$end
$scope module tb_binary_to_excess3 $end
$var wire 4 ! excess3 [3:0] $end
$var reg 4 " binary [3:0] $end
$scope module uut $end
$var wire 4 # binary [3:0] $end
$var wire 4 $ excess3 [3:0] $end
$upscope $end
$upscope $end
$enddefinitions $end
$comment Show the parameter values. $end
$dumpall
$end
#0
$dumpvars
b11 $
b0 #
b0 "
b11 !
$end
#10000
b100 !
b100 $
b1 "
b1 #
#20000
b101 !
b101 $
b10 "
b10 #
#30000
b110 !
b110 $
b11 "
b11 #
#40000
b111 !
b111 $
b100 "
b100 #
#50000
b1000 !
b1000 $
b101 "
b101 #
#60000
b1001 !
b1001 $
b110 "
b110 #
#70000
b1010 !
b1010 $
b111 "
b111 #
#80000
b1011 !
b1011 $
b1000 "
b1000 #
#90000
b1100 !
b1100 $
b1001 "
b1001 #
#100000
b1101 !
b1101 $
b1010 "
b1010 #
#110000
b1110 !
b1110 $
b1011 "
b1011 #
#120000
b1111 !
b1111 $
b1100 "
b1100 #
#130000
b0 !
b0 $
b1101 "
b1101 #
#140000
b1 !
b1 $
b1110 "
b1110 #
#150000
b10 !
b10 $
b1111 "
b1111 #
