experiment-4/binary_to_gray_3bit.v
module binary_to_gray (
    input [2:0] binary,  // 3-bit Binary input
    output [2:0] gray    // 3-bit Gray code output
);

    // Conversion logic: Gray[i] = Binary[i] ^ Binary[i+1]
    assign gray[2] = binary[2];                // MSB stays the same
    assign gray[1] = binary[2] ^ binary[1];    // XOR for each subsequent bit
    assign gray[0] = binary[1] ^ binary[0];

endmodule

experiment-4/tb_binary_to_gray_3bit.v
`timescale 1ns / 1ps

module tb_binary_to_gray;
    // Inputs
    reg [2:0] binary;
    
    // Outputs
    wire [2:0] gray;
    
    // Instantiate the Unit Under Test (UUT)
    binary_to_gray uut (
        .binary(binary),
        .gray(gray)
    );

    // Simulation control
    initial begin
        // Create VCD file for waveform dumping
        $dumpfile("binary_to_gray.vcd");   // Create the VCD file
        $dumpvars(0, tb_binary_to_gray);   // Dump all variables of the testbench

        // Display output on the console
        $monitor("Time = %0d, Binary = %b, Gray = %b", $time, binary, gray);
        
        // Test cases
        binary = 3'b000; #10;
        binary = 3'b001; #10;
        binary = 3'b010; #10;
        binary = 3'b011; #10;
        binary = 3'b100; #10;
        binary = 3'b101; #10;
        binary = 3'b110; #10;
        binary = 3'b111; #10;

        // End simulation
        $finish;
    end
endmodule

experiment-4/binary_to_gray.vcd
$date
	Thu Oct  3 19:09:55 2024
$end
$version
	Icarus Verilog
$end
$timescale
	1ps
$end
$scope module tb_binary_to_gray $end
$var wire 3 ! gray [2:0] $end
$var reg 3 " binary [2:0] $end
$scope module uut $end
$var wire 3 # binary [2:0] $end
$var wire 3 $ gray [2:0] $end
$upscope $end
$upscope $end
$enddefinitions $end
$comment Show the parameter values. $end
$dumpall
$end
#0
$dumpvars
b0 $
b0 #
b0 "
b0 !
$end
#10000
b1 !
b1 $
b1 "
b1 #
#20000
b11 !
b11 $
b10 "
b10 #
#30000
b10 !
b10 $
b11 "
b11 #
#40000
b110 !
b110 $
b100 "
b100 #
#50000
b111 !
b111 $
b101 "
b101 #
#60000
b101 !
b101 $
b110 "
b110 #
#70000
b100 !
b100 $
b111 "
b111 #
