experiment-4/excess3_to_binary.v
module excess3_to_binary (
    input [2:0] excess3,  // 3-bit Excess-3 input
    output [2:0] binary   // 3-bit Binary output
);

    // Conversion logic: Binary = Excess-3 - 3
    assign binary = excess3 - 3'b011;  // Subtract 3 (011 in binary)

endmodule

experiment-4/tb_excess3_to_binary.v
`timescale 1ns / 1ps

module tb_excess3_to_binary;
    // Inputs
    reg [2:0] excess3;
    
    // Outputs
    wire [2:0] binary;
    
    // Instantiate the Unit Under Test (UUT)
    excess3_to_binary uut (
        .excess3(excess3),
        .binary(binary)
    );

    // Simulation control
    initial begin
        // Create VCD file for waveform dumping
        $dumpfile("excess3_to_binary.vcd");   // Create the VCD file
        $dumpvars(0, tb_excess3_to_binary);   // Dump all variables of the testbench

        // Display output on the console
        $monitor("Time = %0d, Excess-3 = %b, Binary = %b", $time, excess3, binary);
        
        // Test cases for valid Excess-3 inputs
        excess3 = 3'b011; #10;  // Excess-3 = 3 -> Binary = 0
        excess3 = 3'b100; #10;  // Excess-3 = 4 -> Binary = 1
        excess3 = 3'b101; #10;  // Excess-3 = 5 -> Binary = 2
        excess3 = 3'b110; #10;  // Excess-3 = 6 -> Binary = 3
        excess3 = 3'b111; #10;  // Excess-3 = 7 -> Binary = 4
        excess3 = 3'b000; #10;  // Excess-3 = 0 (invalid input)
        excess3 = 3'b001; #10;  // Excess-3 = 1 (invalid input)
        excess3 = 3'b010; #10;  // Excess-3 = 2 (invalid input)

        // End simulation
        $finish;
    end
endmodule

experiment-4/excess3_to_binary.vcd
$date
	Thu Oct  3 19:19:30 2024
$end
$version
	Icarus Verilog
$end
$timescale
	1ps
$end
$scope module tb_excess3_to_binary $end
$var wire 3 ! binary [2:0] $end
$var reg 3 " excess3 [2:0] $end
$scope module uut $end
$var wire 3 # excess3 [2:0] $end
$var wire 3 $ binary [2:0] $end
$upscope $end
$upscope $end
$enddefinitions $end
$comment Show the parameter values. $end
$dumpall
$end
#0
$dumpvars
b0 $
b11 #
b11 "
b0 !
$end
#10000
b1 !
b1 $
b100 "
b100 #
#20000
b10 !
b10 $
b101 "
b101 #
#30000
b11 !
b11 $
b110 "
b110 #
#40000
b100 !
b100 $
b111 "
b111 #
#50000
b101 !
b101 $
b0 "
b0 #
#60000
b110 !
b110 $
b1 "
b1 #
#70000
b111 !
b111 $
b10 "
b10 #
