experiment-4/gray_to_binary.v
module gray_to_binary (
    input [3:0] gray,   // 4-bit Gray code input
    output [3:0] binary // 4-bit Binary output
);

    // Conversion logic
    assign binary[3] = gray[3];               // MSB remains the same
    assign binary[2] = gray[3] ^ gray[2];     // XOR for each subsequent bit
    assign binary[1] = binary[2] ^ gray[1];
    assign binary[0] = binary[1] ^ gray[0];

endmodule

experiment-4/tb_gray_to_binary.v
`timescale 1ns / 1ps

module tb_gray_to_binary;
    // Inputs
    reg [3:0] gray;
    
    // Outputs
    wire [3:0] binary;
    
    // Instantiate the Unit Under Test (UUT)
    gray_to_binary uut (
        .gray(gray),
        .binary(binary)
    );

    initial begin
        $dumpfile("gray_to_binary.vcd"); // Create VCD file
        $dumpvars(0, tb_gray_to_binary); // Dump all variables
        // Initialize the Gray code inputs and monitor outputs
        $monitor("Time = %0d, Gray = %b, Binary = %b", $time, gray, binary);

        // Test cases
        gray = 4'b0000; #10;
        gray = 4'b0001; #10;
        gray = 4'b0011; #10;
        gray = 4'b0010; #10;
        gray = 4'b0110; #10;
        gray = 4'b0111; #10;
        gray = 4'b0101; #10;
        gray = 4'b0100; #10;
        gray = 4'b1100; #10;
        gray = 4'b1101; #10;
        gray = 4'b1111; #10;
        gray = 4'b1110; #10;
        gray = 4'b1010; #10;
        gray = 4'b1011; #10;
        gray = 4'b1001; #10;
        gray = 4'b1000; #10;

        // End simulation
        $finish;
    end
endmodule

experiment-4/gray_to_binary.vcd
$date
	Thu Oct  3 19:03:43 2024
$end
$version
	Icarus Verilog
$end
$timescale
	1ps
$end
$scope module tb_gray_to_binary $end
$var wire 4 ! binary [3:0] $end
$var reg 4 " gray [3:0] $end
$scope module uut $end
$var wire 4 # gray [3:0] $end
$var wire 4 $ binary [3:0] $end
$upscope $end
$upscope $end
$enddefinitions $end
$comment Show the parameter values. $end
$dumpall
$end
#0
$dumpvars
b0 $
b0 #
b0 "
b0 !
$end
#10000
b1 !
b1 $
b1 "
b1 #
#20000
b10 !
b10 $
b11 "
b11 #
#30000
b11 !
b11 $
b10 "
b10 #
#40000
b100 !
b100 $
b110 "
b110 #
#50000
b101 !
b101 $
b111 "
b111 #
#60000
b110 !
b110 $
b101 "
b101 #
#70000
b111 !
b111 $
b100 "
b100 #
#80000
b1000 !
b1000 $
b1100 "
b1100 #
#90000
b1001 !
b1001 $
b1101 "
b1101 #
#100000
b1010 !
b1010 $
b1111 "
b1111 #
#110000
b1011 !
b1011 $
b1110 "
b1110 #
#120000
b1100 !
b1100 $
b1010 "
b1010 #
#130000
b1101 !
b1101 $
b1011 "
b1011 #
#140000
b1110 !
b1110 $
b1001 "
b1001 #
#150000
b1111 !
b1111 $
b1000 "
b1000 #
